{
  "name": "Darrell Moran",
  "age": 27,
  "address": {
    "street": "Wusu Point",
    "city": "Waizejah",
    "state": "IL",
    "zip": "09263"
  },
  "contact": {
    "phone": "(838) 824-1932",
    "servicePhone": "800341646"
  },
  "birthday": "1963-02-01T14:18:01.859Z",
  "ip": "97.135.119.66",
  "foo": "bar",
  "profile": {
    "about": "Boc wabufur iskuwi igbano netom muos zic lovujrun atujaruw pokvot gaw tibneos ilupbi gagnatvuz. Kebrakla comufsim gurzoro hav hele owiijo lileza lugna li tajor fi muvcep borgokmo. Tuhab par kangoj rione uluhitat rowohe bufanluj ugcaw ugapo merpihruf muwdosib wo opuahidi pucdug ko goanciv metirze detaez. Hiruc ehkad anrobuko omnawmo zujcigcu unumuno gulav forumer gaspucu tetfi nu ob bur vivujpe lerabwar. Otanowbo erril gucregpuj ka cuba vipon so aciw segudfer go id cafvarfo taz sivowobi. Nowopo butguk vudemuf robifo ahtidige gauzgav jasihren gogegrik hu gi zeb nes riv hi liniji undo.",
    "bio": "Ip dod hewidop gocagad muuboto heziel ivlekot ug waiho tus wodfa naelge. Egwehweh efa dogva hu da hihas uwuse ihrar jic ru wukunniz lu ehpouc jika. Titak laje jotirga koru jiasefe ta ve mut colhabice gevgi sopdev paz beut ifaupmiw zif. Isgu ca pip nobor tosete til mobazo sonzehvic na bumuhob ho vutuw vesawu namiho lu. Suw doihjem fap zum wehovus atedu sef boji ibpijaj tow buzeb cahik vusowga oc ru jinorir fuk."
  },
  "apiKey": "bd0b6c228e3615964bf8f3c0b9df80244b4ceff6af8120c165d3e490aaeabdbf",
  "currency": {
    "code": "BRL",
    "name": "Brazil Real"
  }
}