{
  "name": "Marvin Gutierrez",
  "age": 20,
  "address": {
    "street": "Jaut Pike",
    "city": "Zuhjerni",
    "state": "CA",
    "zip": "23386"
  },
  "contact": {
    "phone": "(289) 260-7949",
    "servicePhone": "800975282"
  },
  "birthday": "1981-04-11T03:48:02.502Z",
  "ip": "119.210.154.3",
  "foo": "bar",
  "profile": {
    "about": "Wu su heuritot bu wemtan me jobako gojuj logmaco cuwurjon giwon fohopa gi. Ra ol igaipupa def ji dofrujuju ajurgal hiskihu kineptat von bonnaj buwzaga. Futhoher delog maku jupzici piwossap bipkuv hizme ahozumaj noctir colgiw jubikka ereonzal opu. Uwuppah ebupa vavubus kogwocuz vam aptug ed uja coti fow pe de. Ericat jeweditu guvfoc egucibgat kaopo tu mo boc geh gat pebdaspu wokak tu hadlurto po zavki saganjaj. Wovbeh iker he kev evi kap sih nefeiw fefkilam acicub ji ewi tuomu. Cehom pusoj nemwu lalwon vubbiz zuvalu fetuha vob vi gezebe ekogide volav ecinitot sized lu racvure kidmo.",
    "bio": "Ov ga guz evota narsom wibparvat wuhe pekfej kuzighe um mado opasu nolis uzfub wadtupir togze. Ip lu vimub jot avfo kiwawha uguko ilti titu radcer tozleg zoturuto jogolre bubevzis pu ipco setwashe purju. Rinfigno jejo af zorubic pudu eb eweal sob voji cizohfet alumaf ge tapkot beazo gile fi vaagohi babvow. Rogji bogcos ve jafugo igamuzot ovu zittimuc vejpaza coulufe tiw umsodlil asmimaf kum ge abhuh godis mevduce co. Zapne le ojiref mobbe vu kicow mo ucucu to rodtifduk tilej pinu upu lic dauzounu lucehte ihoposek."
  },
  "apiKey": "4abc0c839e8904117656578e900b31dd9895a5bc4789329b782bdacccfb0ef3e",
  "currency": {
    "code": "KYD",
    "name": "Cayman Islands Dollar"
  }
}